topsis_tushar_102303176/__init__.py
topsis_tushar_102303176/topsis.py
topsis_tushar_102303176-1.0.0.dist-info/METADATA
topsis_tushar_102303176-1.0.0.dist-info/WHEEL
topsis_tushar_102303176-1.0.0.dist-info/entry_points.txt
topsis_tushar_102303176-1.0.0.dist-info/top_level.txt
topsis_tushar_102303176-1.0.0.dist-info/RECORD
