Metadata-Version: 2.4
Name: Topsis-Tushar-102303176
Version: 1.0.0
Summary: TOPSIS implementation
Requires-Python: >=3.7
Requires-Dist: pandas
Requires-Dist: numpy
